sprintforecast/__init__.py
sprintforecast/cli.py
sprintforecast/dependency_fetcher.py
sprintforecast/distributions.py
sprintforecast/forecast.py
sprintforecast/github_client.py
sprintforecast/issue_fetcher.py
sprintforecast/project_board.py
sprintforecast/queue_simulator.py
sprintforecast/rng_singleton.py
sprintforecast/size.py
sprintforecast/sprint_intake.py
sprintforecast/strategies.py
sprintforecast/symbolic_metrics.py
sprintforecast/ticket.py
sprintforecast/timeline_fetcher.py
sprintforecast/triad_fetcher.py
sprintforecast/types.py
sprintforecast-0.2.9.dist-info/licenses/LICENSE
sprintforecast-0.2.9.dist-info/METADATA
sprintforecast-0.2.9.dist-info/WHEEL
sprintforecast-0.2.9.dist-info/entry_points.txt
sprintforecast-0.2.9.dist-info/top_level.txt
sprintforecast-0.2.9.dist-info/RECORD
