Metadata-Version: 2.4
Name: sprintforecast
Version: 0.2.9
Summary: Hierarchical Bayesian sprint forecasting and intake planning
Requires-Python: >=3.10
License-File: LICENSE
Requires-Dist: numpy>=1.26
Requires-Dist: scipy>=1.12
Requires-Dist: typer[all]>=0.12
Requires-Dist: requests>=2.32
Requires-Dist: sympy>=1.14
Requires-Dist: graphql-core>=3.2
Provides-Extra: dev
Requires-Dist: pytest>=8; extra == "dev"
Requires-Dist: ruff>=0.4; extra == "dev"
Requires-Dist: mypy>=1.10; extra == "dev"
Dynamic: license-file
